python_workfront-0.8.0.dist-info/DESCRIPTION.rst
python_workfront-0.8.0.dist-info/METADATA
python_workfront-0.8.0.dist-info/RECORD
python_workfront-0.8.0.dist-info/WHEEL
python_workfront-0.8.0.dist-info/metadata.json
python_workfront-0.8.0.dist-info/top_level.txt
tests/__init__.py
tests/helpers.py
tests/test_docs.py
tests/test_generate.py
tests/test_get_api_key.py
tests/test_meta.py
tests/test_post_generate.py
tests/test_script.py
tests/test_session.py
workfront/__init__.py
workfront/generate.py
workfront/get_api_key.py
workfront/meta.py
workfront/script.py
workfront/session.py
workfront/six.py
workfront/versions/__init__.py
workfront/versions/unsupported.py
workfront/versions/v40.py
